odoo/addons/stock_buffer_route/README.rst
odoo/addons/stock_buffer_route/__init__.py
odoo/addons/stock_buffer_route/__manifest__.py
odoo/addons/stock_buffer_route/i18n/es.po
odoo/addons/stock_buffer_route/i18n/it.po
odoo/addons/stock_buffer_route/i18n/pt_BR.po
odoo/addons/stock_buffer_route/i18n/stock_buffer_route.pot
odoo/addons/stock_buffer_route/models/__init__.py
odoo/addons/stock_buffer_route/models/stock_buffer.py
odoo/addons/stock_buffer_route/readme/CONTRIBUTORS.md
odoo/addons/stock_buffer_route/readme/DESCRIPTION.md
odoo/addons/stock_buffer_route/readme/USAGE.md
odoo/addons/stock_buffer_route/static/description/icon.png
odoo/addons/stock_buffer_route/static/description/index.html
odoo/addons/stock_buffer_route/tests/__init__.py
odoo/addons/stock_buffer_route/tests/test_stock_buffer_route.py
odoo/addons/stock_buffer_route/views/stock_buffer_views.xml
odoo/addons/stock_buffer_route/wizards/__init__.py
odoo/addons/stock_buffer_route/wizards/make_procurement_buffer.py
odoo/addons/stock_buffer_route/wizards/make_procurement_buffer_view.xml
odoo_addon_stock_buffer_route-18.0.1.0.0.2.dist-info/METADATA
odoo_addon_stock_buffer_route-18.0.1.0.0.2.dist-info/WHEEL
odoo_addon_stock_buffer_route-18.0.1.0.0.2.dist-info/top_level.txt
odoo_addon_stock_buffer_route-18.0.1.0.0.2.dist-info/RECORD
