Metadata-Version: 2.1
Name: odoo-addon-stock_buffer_route
Version: 18.0.1.0.0.2
Requires-Python: >=3.10
Requires-Dist: odoo-addon-ddmrp==18.0.*
Requires-Dist: odoo==18.0.*
Summary: Allows to force a route to be used when procuring from Stock Buffers
Home-page: https://github.com/OCA/ddmrp
License: LGPL-3
Author: ForgeFlow, Camptocamp, Odoo Community Association (OCA)
Author-email: support@odoo-community.org
Classifier: Programming Language :: Python
Classifier: Framework :: Odoo
Classifier: Framework :: Odoo :: 18.0
Classifier: License :: OSI Approved :: GNU Lesser General Public License v3 (LGPLv3)
